qkbind/__init__.py
qkbind/qkbind.h
qkbind-0.1.1.dist-info/METADATA
qkbind-0.1.1.dist-info/WHEEL
qkbind-0.1.1.dist-info/top_level.txt
qkbind-0.1.1.dist-info/RECORD
